[
    {
        "id": 1,
        "image_path": "https://mybayutcdn.bayut.com/mybayut/wp-content/uploads/Yellow-Wall-Paint-AR27052021-768x480.jpg",
        "title": "الدهانات المائية",
        "desc": "تُعرف الدهانات ذات الأساس المائي بسهولة استخدامها على الحوائط الداخلية والخارجية مقارنةً مع انواع دهانات حوائط الأُخرى، وتتميّز بما يلي:",
        "info": [
            "صعوبة نمو العفن عليها",
            "سهولة التنظيف",
            "تخلو من المركبات العضوية السامة",
            "تمتلك خيارات لا محدودة من الألوان",
            "مقاومة للتشقّق وتحافظ على لونها مع مرور الوقت"
        ]
    },
    {
        "id": 2,
        "image_path": "https://smddecoration.com/smdturkiyedecoration/vi/blog/4114/%D8%A7%D9%84%D8%AF%D9%87%D8%A7%D9%86-%D8%A7%D9%84%D8%B2%D9%8A%D8%AA%D9%8A.webp",
        "title": "الدهانات الزيتية ",
        "desc": " تتميز الدهانات الزيتية بألوانها الغنية وإمكانية استخدامها على جميع الأسطح تقريباً، ولكن يجب الحذر عند التعامل معها نظراً لانبعاث أبخرة قوية وسامة منها. تتعدّد مزايا الدهانات ذات الأساس الزيتي، ونذكر منها:",
        "info": [
            "اللّمعان",
            "لا تتأثر بالظروف المناخية، مثل الحرارة والرطوبة",
            "تتناسب مع الغرف عالية الرطوبة، مثل الحمام أو المطبخ والمناطق كثيرة الاستخدام، مثل غرف الجلوس وغرفة الأطفال",
            "إمكانية إجراء تعديلات عليها نظراً لأنها تحتاج لوقت طويل حتى تجف"
        ]
    },
    {
        "id": 3,
        "image_path": "https://www.elbeeet.com/wp-content/uploads/2016/12/home-painting-and-decorating-e1437009382777.jpg",
        "title": "الدهانات البلاستيك ",
        "desc": " تُعتبر دهانات البلاستيك من أكثر انواع الصباغة الحديثة المائية انتشاراً في الوقت الحالي:",
        "info": [
            "لسهولة تطبيقها على الجدران وأسعارها المناسبة للجميعن",
            "لا تتأثر بالظروف المناخية، مثل الحرارة والرطوبة",
            "تتناسب مع الغرف عالية الرطوبة، مثل الحمام أو المطبخ والمناطق كثيرة الاستخدام، مثل غرف الجلوس وغرفة الأطفال",
            "إمكانية إجراء تعديلات عليها نظراً لأنها تحتاج لوقت طويل حتى تجف"
        ]
    },
    {
        "id": 4,
        "image_path": "https://mybayutcdn.bayut.com/mybayut/wp-content/uploads/Types-of-wall-and-wood-paints-_-Body-3-20-3-24-ar-1024x640.jpg",
        "title": "دهانات القطيفة",
        "desc": " تُعرف دهانات القطيفة بأنها من أرقى وأفخم أنواع الدهانات الديكورية على الإطلاق، إذ تتميّز بمظهرها اللؤلؤي الكريستالي الذي يُضفي أناقةً وفخامةً على الجدران",
        "info": [
            "يتمتّع بثباته لفترة زمنية طويلة",
            "يتميّز بسهولة تنظيفه",
            "يُعرف كذلك بأنه صديق للبيئة وغير قابل للاشتعال"
        ]
    }



]
